verihubs/__init__.py
verihubs-0.0.3.dist-info/METADATA
verihubs-0.0.3.dist-info/WHEEL
verihubs-0.0.3.dist-info/licenses/LICENSE
verihubs-0.0.3.dist-info/RECORD
